ejtraderIQ/__init__.py
ejtraderIQ/api.py
ejtraderIQ/constants.py
ejtraderIQ/country_id.py
ejtraderIQ/easyapi.py
ejtraderIQ/expiration.py
ejtraderIQ/global_value.py
ejtraderIQ/stable_api.py
ejtraderIQ/http/__init__.py
ejtraderIQ/http/appinit.py
ejtraderIQ/http/auth.py
ejtraderIQ/http/billing.py
ejtraderIQ/http/buyback.py
ejtraderIQ/http/changebalance.py
ejtraderIQ/http/events.py
ejtraderIQ/http/getprofile.py
ejtraderIQ/http/getregdata.py
ejtraderIQ/http/login.py
ejtraderIQ/http/loginv2.py
ejtraderIQ/http/logout.py
ejtraderIQ/http/profile.py
ejtraderIQ/http/register.py
ejtraderIQ/http/resource.py
ejtraderIQ/http/token.py
ejtraderIQ/ws/__init__.py
ejtraderIQ/ws/client.py
ejtraderIQ/ws/chanels/__init__.py
ejtraderIQ/ws/chanels/api_game_betinfo.py
ejtraderIQ/ws/chanels/api_game_getoptions.py
ejtraderIQ/ws/chanels/base.py
ejtraderIQ/ws/chanels/buy_place_order_temp.py
ejtraderIQ/ws/chanels/buyback.py
ejtraderIQ/ws/chanels/buyv2.py
ejtraderIQ/ws/chanels/buyv3.py
ejtraderIQ/ws/chanels/cancel_order.py
ejtraderIQ/ws/chanels/candles.py
ejtraderIQ/ws/chanels/change_auto_margin_call.py
ejtraderIQ/ws/chanels/change_tpsl.py
ejtraderIQ/ws/chanels/changebalance.py
ejtraderIQ/ws/chanels/close_position.py
ejtraderIQ/ws/chanels/digital_option.py
ejtraderIQ/ws/chanels/get_available_leverages.py
ejtraderIQ/ws/chanels/get_balances.py
ejtraderIQ/ws/chanels/get_deferred_orders.py
ejtraderIQ/ws/chanels/get_financial_information.py
ejtraderIQ/ws/chanels/get_order.py
ejtraderIQ/ws/chanels/get_overnight_fee.py
ejtraderIQ/ws/chanels/get_positions.py
ejtraderIQ/ws/chanels/heartbeat.py
ejtraderIQ/ws/chanels/instruments.py
ejtraderIQ/ws/chanels/leaderboard.py
ejtraderIQ/ws/chanels/sell_option.py
ejtraderIQ/ws/chanels/setactives.py
ejtraderIQ/ws/chanels/ssid.py
ejtraderIQ/ws/chanels/strike_list.py
ejtraderIQ/ws/chanels/subscribe.py
ejtraderIQ/ws/chanels/traders_mood.py
ejtraderIQ/ws/chanels/unsubscribe.py
ejtraderIQ/ws/chanels/user.py
ejtraderIQ/ws/objects/__init__.py
ejtraderIQ/ws/objects/base.py
ejtraderIQ-1.1.1.dist-info/METADATA
ejtraderIQ-1.1.1.dist-info/WHEEL
ejtraderIQ-1.1.1.dist-info/top_level.txt
ejtraderIQ-1.1.1.dist-info/RECORD
