Metadata-Version: 2.1
Name: ejtraderIQ
Version: 1.1.1
Summary: IQ Option API for python
Home-page: https://github.com/ejtraderLabs/ejtraderIQ
Author: Emerson Pedroso
Author-email: emerson@ejtrader.com
